{
  "users": [
    {
      "id": 399059124,
      "is_bot": false,
      "first_name": "Sasha",
      "username": "sraken",
      "language_code": "ru",
      "chatId": 399059124
    },
    {
      "id": 334173112,
      "is_bot": false,
      "first_name": "Osadchyi",
      "last_name": "Yevhenii",
      "username": "eosadchyi",
      "language_code": "en",
      "chatId": 334173112
    },
    {
      "id": 511025038,
      "is_bot": false,
      "first_name": "Anton",
      "last_name": "Mudrenok",
      "username": "just_a_ride",
      "chatId": 511025038
    }
  ],
  "xrpPrice": 0.649701
}